linc/__init__.py
linc/cli.py
linc/convertion.py
linc/models.py
linc/reader.py
linc/utils.py
linc/config/__init__.py
linc/config/default-config.toml
linc/config/models.py
linc/config/read.py
linc/parse/__init__.py
linc/parse/constants.py
linc/parse/dataset.py
linc/parse/file.py
linc/parse/header.py
linc/parse/utils.py
linc/write/common.py
linc/write/writer_nc.py
linc-3.0.6.dist-info/METADATA
linc-3.0.6.dist-info/WHEEL
linc-3.0.6.dist-info/entry_points.txt
linc-3.0.6.dist-info/RECORD
