Metadata-Version: 2.4
Name: linc
Version: 3.0.6
Summary: A package to handle LICEL Binary format
Author-email: Juan Diego <jdlar@eafit.edu.co>
License: MIT
Classifier: Framework :: Pydantic
Classifier: Framework :: Pydantic :: 2
Classifier: Intended Audience :: Science/Research
Classifier: License :: OSI Approved :: MIT License
Classifier: Operating System :: OS Independent
Classifier: Programming Language :: Python
Classifier: Programming Language :: Python :: 3
Classifier: Programming Language :: Python :: 3 :: Only
Classifier: Programming Language :: Python :: 3.10
Classifier: Programming Language :: Python :: 3.11
Classifier: Programming Language :: Python :: 3.12
Classifier: Programming Language :: Python :: 3.13
Classifier: Topic :: Scientific/Engineering :: Atmospheric Science
Requires-Python: >=3.10
Requires-Dist: netcdf4<2,>=1.6.2
Requires-Dist: numpy<2.1,>=2.0.2
Requires-Dist: pydantic>=2.10.6
Requires-Dist: tomli<3,>=2.0.1
Requires-Dist: typer<1,>=0.15.1
